{
  "id": "mon_feral_human_telekin",
  "fg": [
    { "weight": 1, "sprite": "mon_feral_human_telekin" },
    { "weight": 1, "sprite": "mon_feral_human_telekin_1" },
    { "weight": 1, "sprite": "mon_feral_human_telekin_2" },
    { "weight": 1, "sprite": "mon_feral_human_telekin_3" },
    { "weight": 1, "sprite": "mon_feral_human_telekin_4" },
    { "weight": 1, "sprite": "mon_feral_human_telekin_5" },
    { "weight": 1, "sprite": "mon_feral_human_telekin_6" },
    { "weight": 1, "sprite": "mon_feral_human_telekin_7" }
  ],
  "bg": ["bg_big_normal_shadow"],
  "rotates": false
}